gamesolver/GameManager.py
gamesolver/__init__.py
gamesolver/example.py
gamesolver/util.py
gamesolver/Games/Game.py
gamesolver/Games/Nim.py
gamesolver/Games/TTT.py
gamesolver/Games/TierGame.py
gamesolver/Games/__init__.py
gamesolver/Solvers/Solver.py
gamesolver/Solvers/TierSolver.py
gamesolver/Solvers/__init__.py
gamesolver/tests/__init__.py
gamesolver/tests/test.py
gamesolver/tests/testTTT.py
gamesolver-0.0.2.dist-info/LICENSE
gamesolver-0.0.2.dist-info/METADATA
gamesolver-0.0.2.dist-info/WHEEL
gamesolver-0.0.2.dist-info/top_level.txt
gamesolver-0.0.2.dist-info/RECORD
